kkba/LICENSE
kkba/README.md.tmpl
kkba/VERSION
kkba/__init__.py
kkba/__main__.py
kkba/common.py
kkba/feapder_air_spider_template.tmpl
kkba/parse_curl.py
kkba/proxy.py
kkba/scrapy_template.tmpl
kkba/ulti.py
kkba-0.8.16.dist-info/LICENSE
kkba-0.8.16.dist-info/METADATA
kkba-0.8.16.dist-info/WHEEL
kkba-0.8.16.dist-info/entry_points.txt
kkba-0.8.16.dist-info/top_level.txt
kkba-0.8.16.dist-info/zip-safe
kkba-0.8.16.dist-info/RECORD
