Metadata-Version: 2.1
Name: kkba
Version: 0.8.16
Summary: A Library to Convert Curl to Python Requests File
Home-page: https://github.com/kaikeba/kkba
Author: dylan
Author-email: shddylan@163.com
License: UNKNOWN
Keywords: curl pypi
Platform: any
Requires-Python: >=3.6
License-File: LICENSE
Requires-Dist: pyperclip (>=1.8.0)
Requires-Dist: rich (>=9.13.0)
Requires-Dist: requests
